MeroShareAPI/__init__.py
MeroShareAPI-0.0.5.dist-info/LICENSE
MeroShareAPI-0.0.5.dist-info/METADATA
MeroShareAPI-0.0.5.dist-info/WHEEL
MeroShareAPI-0.0.5.dist-info/top_level.txt
MeroShareAPI-0.0.5.dist-info/RECORD
