Metadata-Version: 2.1
Name: MeroShareAPI
Version: 0.0.5
Summary: Mero Share API
Home-page: https://github.com/punkholic/meroshare_API
Author: Niraj Ghimire
Author-email: nirajghimirexyz@gmail.com
License: UNKNOWN
Project-URL: Bug Tracker, https://github.com/punkholic/meroshare_API/issues
Keywords: API,MeroShare,MeroShareAPI,NepalIPO,IPO,punkholic
Platform: UNKNOWN
Classifier: Development Status :: 1 - Planning
Classifier: Intended Audience :: Developers
Classifier: License :: OSI Approved :: MIT License
Classifier: Programming Language :: Python :: 3
Classifier: Operating System :: Unix
Classifier: Operating System :: MacOS :: MacOS X
Classifier: Operating System :: Microsoft :: Windows
Requires-Dist: requests
Requires-Dist: simplejson
